djutil/__init__.py
djutil/autocompletes.py
djutil/models.py
djutil/str.py
dj_util-0.0.0.dev1.dist-info/LICENSE
dj_util-0.0.0.dev1.dist-info/WHEEL
dj_util-0.0.0.dev1.dist-info/METADATA
dj_util-0.0.0.dev1.dist-info/RECORD
