Metadata-Version: 2.1
Name: dj-util
Version: 0.0.0.dev1
Summary: Django Utilities
Home-page: https://GitHub.com/Django-AI/Dj-Util
License: MIT
Keywords: Django,utilities,utils,util
Author: The Vinh LUONG (LƯƠNG Thế Vinh)
Author-email: TheVinhLuong@gmail.com
Maintainer: The Vinh LUONG (LƯƠNG Thế Vinh)
Maintainer-email: TheVinhLuong@gmail.com
Requires-Python: >=3.8,<4.0
Classifier: Development Status :: 5 - Production/Stable
Classifier: Environment :: MacOS X
Classifier: Environment :: Win32 (MS Windows)
Classifier: Framework :: Django
Classifier: Framework :: Django :: 4.0
Classifier: Intended Audience :: Developers
Classifier: License :: OSI Approved :: MIT License
Classifier: Operating System :: MacOS
Classifier: Operating System :: MacOS :: MacOS X
Classifier: Operating System :: Microsoft
Classifier: Operating System :: Microsoft :: Windows
Classifier: Operating System :: Microsoft :: Windows :: Windows 10
Classifier: Operating System :: Microsoft :: Windows :: Windows 7
Classifier: Operating System :: Microsoft :: Windows :: Windows 8
Classifier: Operating System :: Microsoft :: Windows :: Windows 8.1
Classifier: Operating System :: OS Independent
Classifier: Operating System :: Other OS
Classifier: Operating System :: POSIX
Classifier: Operating System :: POSIX :: Linux
Classifier: Programming Language :: Python
Classifier: Programming Language :: Python :: 3
Classifier: Programming Language :: Python :: 3.10
Classifier: Programming Language :: Python :: 3.11
Classifier: Programming Language :: Python :: 3.8
Classifier: Programming Language :: Python :: 3.9
Classifier: Topic :: Scientific/Engineering
Classifier: Topic :: Software Development
Classifier: Topic :: Software Development :: Libraries
Classifier: Topic :: Software Development :: Libraries :: Python Modules
Requires-Dist: Django (>=4.1,<5.0)
Requires-Dist: Django-Autocomplete-Light (>=3.9.4,<4.0.0)
Requires-Dist: Django-Model-Utils (>=4.2.0,<5.0.0)
Project-URL: Documentation, https://Django-AI.GitHub.io/Dj-Util
Project-URL: GitHub, https://GitHub.com/Django-AI/Dj-Util
Project-URL: Repository, https://GitHub.com/Django-AI/Dj-Util
